AUTHOR
LICENSE
MANIFEST.in
README.rst
ez_setup.py
setup.py
piws_setup/__init__.py
piws_setup/info.py
piws_setup/piws_setup
piws_setup.egg-info/PKG-INFO
piws_setup.egg-info/SOURCES.txt
piws_setup.egg-info/dependency_links.txt
piws_setup.egg-info/requires.txt
piws_setup.egg-info/top_level.txt
piws_setup/configs/3.20.conf
piws_setup/configs/__init__.py
piws_setup/configs/generate_conf_3_20.py