Metadata-Version: 1.1
Name: piws-setup
Version: 1.1.1
Summary: PIWS setup
Home-page: https://github.com/neurospin/piws_setup.git
Author: NSAp developers
Author-email: antoine.grigis@cea.fr
License: CeCILL-B
Platform: OS Independent
Classifier: Development Status :: 5 - Production/Stable
Classifier: Environment :: Console
Classifier: Operating System :: Unix
Classifier: Programming Language :: Python
Classifier: Topic :: Scientific/Engineering
Classifier: Topic :: Utilities
